domapping/__init__.py
domapping/cli.py
domapping/errors.py
domapping/mapping.py
domapping/templating.py
domapping/version.py
domapping-1.0.0a1.dist-info/top_level.txt
domapping-1.0.0a1.dist-info/entry_points.txt
domapping-1.0.0a1.dist-info/METADATA
domapping-1.0.0a1.dist-info/DESCRIPTION.rst
domapping-1.0.0a1.dist-info/metadata.json
domapping-1.0.0a1.dist-info/WHEEL
domapping-1.0.0a1.dist-info/RECORD
